{  
   "mappings":{  
      "transaction":{  
         "properties":{  
            "acheteur":{  
               "properties":{  
                  "civilite":{  
                     "type":"text",
                     "fields":{  
                        "raw":{  
                           "type":"keyword"
                        }
                     }
                  },
                  "nom":{  
                     "type":"text",
                     "fields":{  
                        "raw":{  
                           "type":"keyword"
                        }
                     }
                  },
                  "prenom":{  
                     "type":"text",
                     "fields":{  
                        "raw":{  
                           "type":"keyword"
                        }
                     }
                  },
                  "age":{  
                     "type":"float"
                  },
                  "email":{  
                     "type":"text",
                     "fields":{  
                        "raw":{  
                           "type":"keyword"
                        }
                     }
                  }
               }
            },
            "game":{  
               "properties":{  
                  "nom":{  
                     "type":"text",
                     "fields":{  
                        "raw":{  
                           "type":"keyword"
                        }
                     }
                  },
                  "jour":{  
                     "type":"text",
                     "fields":{  
                        "raw":{  
                           "type":"keyword"
                        }
                     }
                  },
                  "horaire":{  
                     "type":"text",
                     "fields":{  
                        "raw":{  
                           "type":"keyword"
                        }
                     }
                  },
                  "vr":{  
                     "type":"text",
                     "fields":{  
                        "raw":{  
                           "type":"keyword"
                        }
                     }
                  }
               }
            },
            "reservation":{  
               "type":"nested",
               "properties":{  
                  "spectateur":{  
                     "properties":{  
                        "civilite":{  
                           "type":"text",
                           "fields":{  
                              "raw":{  
                                 "type":"keyword"
                              }
                           }
                        },
                        "nom":{  
                           "type":"text",
                           "fields":{  
                              "raw":{  
                                 "type":"keyword"
                              }
                           }
                        },
                        "prenom":{  
                           "type":"text",
                           "fields":{  
                              "raw":{  
                                 "type":"keyword"
                              }
                           }
                        },
                        "age":{  
                           "type":"float"
                        },
                        "email":{  
                           "type":"text",
                           "fields":{  
                              "raw":{  
                                 "type":"keyword"
                              }
                           }
                        }
                     }
                  },
                  "tarif":{  
                     "type":"text",
                     "fields":{  
                        "raw":{  
                           "type":"keyword"
                        }
                     }
                  }
               }
            }
         }
      }
   }
}